README.md
setup.py
project_template_python/__init__.py
project_template_python/utils.py
project_template_python.egg-info/PKG-INFO
project_template_python.egg-info/SOURCES.txt
project_template_python.egg-info/dependency_links.txt
project_template_python.egg-info/requires.txt
project_template_python.egg-info/top_level.txt